rtl/cdc/pulse_synchronizer/slow_to_fast_domain.sv
// From Slow Domain to Fast Domain

module pulse_synchronizer(
    // Slow Domain Interface (Source)
    input  logic clk_slow,
    input  logic rst_slow_n,
    input  logic pulse_slow_in,    // 1-cycle pulse in slow domain

    // Fast Domain Interface (Destination)
    input  logic clk_fast,
    input  logic rst_fast_n,
    output logic pulse_fast_out    // Reconstructed 1-cycle pulse in fast domain
);

    // Since the source clock (slow) is slower than the destination clock (fast),
    // a 1-cycle pulse in the slow domain is guaranteed to be wider than the fast clock period.
    // Thus, it will not be missed by the fast clock.
    // We only need a 2-FF synchronizer followed by a rising-edge detector in the fast domain.

    logic sync_ff1, sync_ff2;

    // 2-FF Synchronizer in the Fast Domain
    always_ff @(posedge clk_fast or negedge rst_fast_n) begin
        if (!rst_fast_n) begin
            sync_ff1 <= 1'b0;
            sync_ff2 <= 1'b0;
        end else begin
            sync_ff1 <= pulse_slow_in;
            sync_ff2 <= sync_ff1;
        end
    end

    // Edge Detector in the Fast Domain
    logic sync_ff3;

    always_ff @(posedge clk_fast or negedge rst_fast_n) begin
        if (!rst_fast_n) begin
            sync_ff3 <= 1'b0;
        end else begin
            sync_ff3 <= sync_ff2; // Delayed version of synchronized signal
        end
    end

    // Detect rising edge (0 -> 1 transition) in the fast domain
    assign pulse_fast_out = sync_ff2 & ~sync_ff3;

endmodule


// Testbench
module tb;

    // Slow Domain Interface
    logic clk_slow;
    logic rst_slow_n;
    logic pulse_slow_in;

    // Fast Domain Interface
    logic clk_fast;
    logic rst_fast_n;
    logic pulse_fast_out;

    // Instantiate UUT
    pulse_synchronizer dut (
        .clk_slow(clk_slow),
        .rst_slow_n(rst_slow_n),
        .pulse_slow_in(pulse_slow_in),
        .clk_fast(clk_fast),
        .rst_fast_n(rst_fast_n),
        .pulse_fast_out(pulse_fast_out)
    );

    // Slow clock generation (20 MHz, 50ns period)
    always begin
        #25 clk_slow = ~clk_slow;
    end

    // Fast clock generation (100 MHz, 10ns period)
    always begin
        #5 clk_fast = ~clk_fast;
    end

    // Monitor reconstructed pulses in fast domain
    always @(posedge clk_fast) begin
        if (pulse_fast_out) begin
            $display("[Time %0t ns] FAST: Reconstructed pulse detected!", $time);
        end
    end

    initial begin
        $dumpfile("slow_to_fast_waves.vcd");
        $dumpvars(0, tb);

        clk_slow = 0;
        clk_fast = 0;
        rst_slow_n = 0;
        rst_fast_n = 0;
        pulse_slow_in = 0;

        // Release resets
        #40;
        rst_slow_n = 1;
        rst_fast_n = 1;
        $display("[Time %0t ns] Resets released.", $time);
        #20;

        // --- Pulse 1 ---
        $display("[Time %0t ns] SLOW: Sending Pulse 1...", $time);
        @(posedge clk_slow);
        pulse_slow_in <= 1'b1;
        @(posedge clk_slow);
        pulse_slow_in <= 1'b0;

        #200;

        // --- Pulse 2 ---
        $display("[Time %0t ns] SLOW: Sending Pulse 2...", $time);
        @(posedge clk_slow);
        pulse_slow_in <= 1'b1;
        @(posedge clk_slow);
        pulse_slow_in <= 1'b0;

        #200;

        // --- Pulse 3 ---
        $display("[Time %0t ns] SLOW: Sending Pulse 3...", $time);
        @(posedge clk_slow);
        pulse_slow_in <= 1'b1;
        @(posedge clk_slow);
        pulse_slow_in <= 1'b0;

        #200;

        $display("[Time %0t ns] Simulation finished.", $time);
        $finish;
    end

endmodule

rtl/cdc/pulse_synchronizer/slow_to_fast_waves.vcd
$date
    Jul 25, 2026  14:01:25
$end
$version
    TOOL:	xmsim	22.03-s012
$end
$timescale
    1 ns
$end

$scope module tb $end
$var reg       1 !    clk_slow $end
$var reg       1 "    rst_slow_n $end
$var reg       1 #    pulse_slow_in $end
$var reg       1 $    clk_fast $end
$var reg       1 %    rst_fast_n $end
$var reg       1 &    pulse_fast_out $end

$scope module dut $end
$var wire      1 '    clk_slow  $end
$var wire      1 (    rst_slow_n  $end
$var wire      1 )    pulse_slow_in  $end
$var wire      1 *    clk_fast  $end
$var wire      1 +    rst_fast_n  $end
$var reg       1 ,    pulse_fast_out $end
$var reg       1 -    sync_ff1 $end
$var reg       1 .    sync_ff2 $end
$var reg       1 /    sync_ff3 $end
$upscope $end

$upscope $end

$enddefinitions $end
$dumpvars
0!
0"
0#
0$
0%
0&
0'
0(
0)
0*
0+
0,
0-
0.
0/
$end
#5
1$
1*
#10
0$
0*
#15
1$
1*
#20
0$
0*
#25
1!
1$
1*
1'
#30
0$
0*
#35
1$
1*
#40
1"
1%
0$
0*
1(
1+
#45
1$
1*
#50
0!
0$
0*
0'
#55
1$
1*
#60
0$
0*
#65
1$
1*
#70
0$
0*
#75
1!
1$
1*
1'
1#
1)
#80
0$
0*
#85
1$
1*
1-
#90
0$
0*
#95
1$
1*
1.
1,
1&
#100
0!
0$
0*
0'
#105
1$
1*
1/
0,
0&
#110
0$
0*
#115
1$
1*
#120
0$
0*
#125
1!
1$
1*
1'
0#
0)
#130
0$
0*
#135
1$
1*
0-
#140
0$
0*
#145
1$
1*
0.
#150
0!
0$
0*
0'
#155
1$
1*
0/
#160
0$
0*
#165
1$
1*
#170
0$
0*
#175
1!
1$
1*
1'
#180
0$
0*
#185
1$
1*
#190
0$
0*
#195
1$
1*
#200
0!
0$
0*
0'
#205
1$
1*
#210
0$
0*
#215
1$
1*
#220
0$
0*
#225
1!
1$
1*
1'
#230
0$
0*
#235
1$
1*
#240
0$
0*
#245
1$
1*
#250
0!
0$
0*
0'
#255
1$
1*
#260
0$
0*
#265
1$
1*
#270
0$
0*
#275
1!
1$
1*
1'
#280
0$
0*
#285
1$
1*
#290
0$
0*
#295
1$
1*
#300
0!
0$
0*
0'
#305
1$
1*
#310
0$
0*
#315
1$
1*
#320
0$
0*
#325
1!
1$
1*
1'
1#
1)
#330
0$
0*
#335
1$
1*
1-
#340
0$
0*
#345
1$
1*
1.
1,
1&
#350
0!
0$
0*
0'
#355
1$
1*
1/
0,
0&
#360
0$
0*
#365
1$
1*
#370
0$
0*
#375
1!
1$
1*
1'
0#
0)
#380
0$
0*
#385
1$
1*
0-
#390
0$
0*
#395
1$
1*
0.
#400
0!
0$
0*
0'
#405
1$
1*
0/
#410
0$
0*
#415
1$
1*
#420
0$
0*
#425
1!
1$
1*
1'
#430
0$
0*
#435
1$
1*
#440
0$
0*
#445
1$
1*
#450
0!
0$
0*
0'
#455
1$
1*
#460
0$
0*
#465
1$
1*
#470
0$
0*
#475
1!
1$
1*
1'
#480
0$
0*
#485
1$
1*
#490
0$
0*
#495
1$
1*
#500
0!
0$
0*
0'
#505
1$
1*
#510
0$
0*
#515
1$
1*
#520
0$
0*
#525
1!
1$
1*
1'
#530
0$
0*
#535
1$
1*
#540
0$
0*
#545
1$
1*
#550
0!
0$
0*
0'
#555
1$
1*
#560
0$
0*
#565
1$
1*
#570
0$
0*
#575
1!
1$
1*
1'
1#
1)
#580
0$
0*
#585
1$
1*
1-
#590
0$
0*
#595
1$
1*
1.
1,
1&
#600
0!
0$
0*
0'
#605
1$
1*
1/
0,
0&
#610
0$
0*
#615
1$
1*
#620
0$
0*
#625
1!
1$
1*
1'
0#
0)
#630
0$
0*
#635
1$
1*
0-
#640
0$
0*
#645
1$
1*
0.
#650
0!
0$
0*
0'
#655
1$
1*
0/
