rtl/cdc/pulse_synchronizer/fast_to_slow_domain_fixed.sv
/* 
- In order to capture the the pulse which is otherwise unseen by the receiving clock domain,
we have to strech the pulse in the fast
- Then pass this through a 2FF synchronizer to remove any metastability
- Then bring the pulse back in the slow receving clock domain by performing an xor operation between the 2FF sync output
and the delayed pulse in slow domain
*/


module pulse_synchronizer (
    // Fast Domain Interface
    input  logic clk_fast,
    input  logic rst_fast_n,
    input  logic pulse_fast_in,   // 1-cycle pulse in fast domain

    // Slow Domain Interface
    input  logic clk_slow,
    input  logic rst_slow_n,
    output logic pulse_slow_out   // Reconstructed 1-cycle pulse in slow domain
);

    //FAST DOMAIN: Convert incoming pulse to a Toggle Signal
    logic fast_toggle;

    always_ff @(posedge clk_fast or negedge rst_fast_n) begin
        if (!rst_fast_n) begin
            fast_toggle <= 1'b0;
        end else if (pulse_fast_in) begin
            fast_toggle <= ~fast_toggle; // Flip bit on every pulse
        end
    end


    // SLOW DOMAIN!
    // 2-FF Synchronizer in Slow Domain to remove any metastability

    logic sync_ff1, sync_ff2;


    // fast_toggle is the input to the slow domain. 

    // ---- INPUT SIGNAL -->  :FF1:  ---- FF1 OUTPUT -----> :FF2: --- OUTPUT WITHOUT ANY METASTABILITY  

    always_ff @(posedge clk_slow or negedge rst_slow_n) begin
        if (!rst_slow_n) begin
            sync_ff1 <= 1'b0;
            sync_ff2 <= 1'b0;
        end else begin
            sync_ff1 <= fast_toggle;
            sync_ff2 <= sync_ff1;
        end
    end

    // Toggle Detector (Delay + XOR)
    logic sync_ff3;

    always_ff @(posedge clk_slow or negedge rst_slow_n) begin
        if (!rst_slow_n) begin
            sync_ff3 <= 1'b0;
        end else begin
            sync_ff3 <= sync_ff2; // 1-cycle delayed version of synchronized toggle
        end
    end

    // XOR detects ANY transition (0 -> 1 or 1 -> 0) to generate a 1-cycle pulse
    assign pulse_slow_out = sync_ff2 ^ sync_ff3;

endmodule



//Testbench
module tb_pulse_synchronizer;

    // Fast Domain Interface
    logic clk_fast;
    logic rst_fast_n;
    logic pulse_fast_in;

    // Slow Domain Interface
    logic clk_slow;
    logic rst_slow_n;
    logic pulse_slow_out;

    pulse_synchronizer dut (
        .clk_fast(clk_fast),
        .rst_fast_n(rst_fast_n),
        .pulse_fast_in(pulse_fast_in),
        .clk_slow(clk_slow),
        .rst_slow_n(rst_slow_n),
        .pulse_slow_out(pulse_slow_out)
    );

    // Fast clock 100 MHz, 10ns period
    always begin
        #5 clk_fast = ~clk_fast;
    end

    // Slow clock generation 20 MHz, 50ns period
    always begin
        #25 clk_slow = ~clk_slow;
    end

    always @(posedge clk_slow) begin
        if (pulse_slow_out) begin
            $display("[Time %0t ns] SLOW: Reconstructed pulse detected!", $time);
        end
    end

    initial begin
        $dumpfile("waves_fixed.vcd");
        $dumpvars(0, tb_pulse_synchronizer);

        clk_fast = 0;
        clk_slow = 0;
        rst_fast_n = 0;
        rst_slow_n = 0;
        pulse_fast_in = 0;

        // Reset
        #40;
        rst_fast_n = 1;
        rst_slow_n = 1;
        $display("[Time %0t ns] Resets released.", $time);
        #20;

        // --- Pulse 1 ---
        $display("[Time %0t ns] FAST: Sending Pulse 1...", $time);
        @(posedge clk_fast);
        pulse_fast_in <= 1'b1;
        @(posedge clk_fast);
        pulse_fast_in <= 1'b0;

        // Delay to resolve pulse in the slow domain
        #200;

        // --- Pulse 2 ---
        $display("[Time %0t ns] FAST: Sending Pulse 2...", $time);
        @(posedge clk_fast);
        pulse_fast_in <= 1'b1;
        @(posedge clk_fast);
        pulse_fast_in <= 1'b0;

        #200;

        // --- Pulse 3 ---
        $display("[Time %0t ns] FAST: Sending Pulse 3...", $time);
        @(posedge clk_fast);
        pulse_fast_in <= 1'b1;
        @(posedge clk_fast);
        pulse_fast_in <= 1'b0;

        #300;

        $display("[Time %0t ns] Simulation finished.", $time);
        $finish;
    end

endmodule

rtl/cdc/pulse_synchronizer/waves_fixed.vcd
$date
    Jul 25, 2026  13:48:47
$end
$version
    TOOL:	xmsim	22.03-s012
$end
$timescale
    1 ns
$end

$scope module tb_pulse_synchronizer $end
$var reg       1 !    clk_fast $end
$var reg       1 "    rst_fast_n $end
$var reg       1 #    pulse_fast_in $end
$var reg       1 $    clk_slow $end
$var reg       1 %    rst_slow_n $end
$var reg       1 &    pulse_slow_out $end

$scope module dut $end
$var wire      1 '    clk_fast  $end
$var wire      1 (    rst_fast_n  $end
$var wire      1 )    pulse_fast_in  $end
$var wire      1 *    clk_slow  $end
$var wire      1 +    rst_slow_n  $end
$var reg       1 ,    pulse_slow_out $end
$var reg       1 -    fast_toggle $end
$var reg       1 .    sync_ff1 $end
$var reg       1 /    sync_ff2 $end
$var reg       1 0    sync_ff3 $end
$upscope $end

$upscope $end

$enddefinitions $end
$dumpvars
0!
0"
0#
0$
0%
0&
0'
0(
0)
0*
0+
0,
0-
0.
0/
00
$end
#5
1!
1'
#10
0!
0'
#15
1!
1'
#20
0!
0'
#25
1$
1!
1'
1*
#30
0!
0'
#35
1!
1'
#40
1"
1%
0!
0'
1+
1(
#45
1!
1'
#50
0$
0!
0'
0*
#55
1!
1'
#60
0!
0'
#65
1!
1'
1#
1)
#70
0!
0'
#75
1$
1!
1'
1*
0#
1-
0)
#80
0!
0'
#85
1!
1'
#90
0!
0'
#95
1!
1'
#100
0$
0!
0'
0*
#105
1!
1'
#110
0!
0'
#115
1!
1'
#120
0!
0'
#125
1$
1!
1'
1*
1.
#130
0!
0'
#135
1!
1'
#140
0!
0'
#145
1!
1'
#150
0$
0!
0'
0*
#155
1!
1'
#160
0!
0'
#165
1!
1'
#170
0!
0'
#175
1$
1!
1'
1*
1/
1,
1&
#180
0!
0'
#185
1!
1'
#190
0!
0'
#195
1!
1'
#200
0$
0!
0'
0*
#205
1!
1'
#210
0!
0'
#215
1!
1'
#220
0!
0'
#225
1$
1!
1'
1*
10
0,
0&
#230
0!
0'
#235
1!
1'
#240
0!
0'
#245
1!
1'
#250
0$
0!
0'
0*
#255
1!
1'
#260
0!
0'
#265
1!
1'
#270
0!
0'
#275
1$
1!
1'
1*
1#
1)
#280
0!
0'
#285
1!
1'
0#
0-
0)
#290
0!
0'
#295
1!
1'
#300
0$
0!
0'
0*
#305
1!
1'
#310
0!
0'
#315
1!
1'
#320
0!
0'
#325
1$
1!
1'
1*
0.
#330
0!
0'
#335
1!
1'
#340
0!
0'
#345
1!
1'
#350
0$
0!
0'
0*
#355
1!
1'
#360
0!
0'
#365
1!
1'
#370
0!
0'
#375
1$
1!
1'
1*
0/
1,
1&
#380
0!
0'
#385
1!
1'
#390
0!
0'
#395
1!
1'
#400
0$
0!
0'
0*
#405
1!
1'
#410
0!
0'
#415
1!
1'
#420
0!
0'
#425
1$
1!
1'
1*
00
0,
0&
#430
0!
0'
#435
1!
1'
#440
0!
0'
#445
1!
1'
#450
0$
0!
0'
0*
#455
1!
1'
#460
0!
0'
#465
1!
1'
#470
0!
0'
#475
1$
1!
1'
1*
#480
0!
0'
#485
1!
1'
1#
1)
#490
0!
0'
#495
1!
1'
0#
1-
0)
#500
0$
0!
0'
0*
#505
1!
1'
#510
0!
0'
#515
1!
1'
#520
0!
0'
#525
1$
1!
1'
1*
1.
#530
0!
0'
#535
1!
1'
#540
0!
0'
#545
1!
1'
#550
0$
0!
0'
0*
#555
1!
1'
#560
0!
0'
#565
1!
1'
#570
0!
0'
#575
1$
1!
1'
1*
1/
1,
1&
#580
0!
0'
#585
1!
1'
#590
0!
0'
#595
1!
1'
#600
0$
0!
0'
0*
#605
1!
1'
#610
0!
0'
#615
1!
1'
#620
0!
0'
#625
1$
1!
1'
1*
10
0,
0&
